iml_query/__init__.py
iml_query/py.typed
iml_query/queries.py
iml_query/tree_sitter_utils.py
iml_query/utils.py
iml_query/processing/__init__.py
iml_query/processing/base.py
iml_query/processing/decomp.py
iml_query/processing/update_top_def.py
iml_query/processing/utils.py
iml_query/processing/vg.py
iml_query-0.5.2.dist-info/METADATA
iml_query-0.5.2.dist-info/WHEEL
iml_query-0.5.2.dist-info/RECORD
