Metadata-Version: 2.4
Name: iml-query
Version: 0.5.2
Summary: Add your description here
Author-email: hongyu <hongyu@imandra.ai>
Requires-Python: >=3.12
Requires-Dist: devtools>=0.12.2
Requires-Dist: rich>=14.1.0
Requires-Dist: sexpdata>=1.0.2
Requires-Dist: structlog>=25.4.0
Requires-Dist: tree-sitter-iml
Requires-Dist: tree-sitter>=0.25.1
